stairs/__init__.py
stairs/core/__init__.py
stairs/core/app_components.py
stairs/core/app/__init__.py
stairs/core/app/components_interface.py
stairs/core/consumer/__init__.py
stairs/core/consumer/iter.py
stairs/core/consumer/standalone.py
stairs/core/flow/__init__.py
stairs/core/flow/flow_context.py
stairs/core/flow/step.py
stairs/core/pipeline/__init__.py
stairs/core/pipeline/data_pipeline.py
stairs/core/pipeline/pipeline_graph.py
stairs/core/pipeline/pipeline_objects/__init__.py
stairs/core/pipeline/pipeline_objects/context.py
stairs/core/pipeline/pipeline_objects/transformation.py
stairs/core/producer/__init__.py
stairs/core/producer/batch.py
stairs/core/producer/signals.py
stairs/core/producer/spark.py
stairs/core/producer/utils.py
stairs/core/project/__init__.py
stairs/core/project/config.py
stairs/core/project/dbs.py
stairs/core/project/signals.py
stairs/core/project/utils.py
stairs/core/session/__init__.py
stairs/core/session/project_session.py
stairs/core/session/signals_session.py
stairs/core/session/step_session.py
stairs/core/session/unique_id_session.py
stairs/core/utils/__init__.py
stairs/core/utils/attrdict.py
stairs/core/utils/execeptions.py
stairs/core/utils/signals.py
stairs/default/__init__.py
stairs/default/default_app/__init__.py
stairs/default/default_app/app_config.py
stairs/default/default_app/consumers.py
stairs/default/default_app/flows.py
stairs/default/default_app/pipelines.py
stairs/default/default_app/producers.py
stairs/default/default_project/__init__.py
stairs/default/default_project/config.py
stairs/default/default_project/manage.py
stairs/services/__init__.py
stairs/services/admin/__init__.py
stairs/services/admin/flask_config.py
stairs/services/admin/server.py
stairs/services/admin/stairs_config.py
stairs/services/config/__init__.py
stairs/services/inspect/__init__.py
stairs/services/inspect/pipelines.py
stairs/services/inspect/utils.py
stairs/services/integrations/__init__.py
stairs/services/integrations/aws.py
stairs_project-0.1.6.1.dist-info/LICENSE
stairs_project-0.1.6.1.dist-info/METADATA
stairs_project-0.1.6.1.dist-info/WHEEL
stairs_project-0.1.6.1.dist-info/entry_points.txt
stairs_project-0.1.6.1.dist-info/top_level.txt
stairs_project-0.1.6.1.dist-info/RECORD
