Metadata-Version: 2.1
Name: stairs-project
Version: 0.1.6.1
Summary: Framework for data processing using data pipelines
Home-page: https://github.com/electronick1/stairs
Author: Aleh Shydlouski
Author-email: oleg.ivye@gmail.com
License: UNKNOWN
Download-URL: https://github.com/electronick1/stairs/archive/0.1.6.tar.gz
Keywords: data-pipeline,data-science,data-engineering,distributed-computing
Platform: UNKNOWN
Requires-Dist: tqdm
Requires-Dist: redis (>=3.0.0)
Requires-Dist: blinker
Requires-Dist: click
Requires-Dist: ujson (>=1.0)
Requires-Dist: ipython (>=6.0.0)
Requires-Dist: stepist (>=0.1.6)
